farcaster/HubService.py
farcaster/Message.py
farcaster/MessageData.py
farcaster/Signer.py
farcaster/__about__.py
farcaster/__init__.py
farcaster/abi/KeyRegistryABI.json
farcaster/abi/SignedKeyRequestMetadataABI.json
farcaster/fcproto/gossip_pb2.py
farcaster/fcproto/gossip_pb2.pyi
farcaster/fcproto/gossip_pb2_grpc.py
farcaster/fcproto/hub_event_pb2.py
farcaster/fcproto/hub_event_pb2.pyi
farcaster/fcproto/hub_event_pb2_grpc.py
farcaster/fcproto/hub_state_pb2.py
farcaster/fcproto/hub_state_pb2.pyi
farcaster/fcproto/hub_state_pb2_grpc.py
farcaster/fcproto/job_pb2.py
farcaster/fcproto/job_pb2.pyi
farcaster/fcproto/job_pb2_grpc.py
farcaster/fcproto/message_pb2.py
farcaster/fcproto/message_pb2.pyi
farcaster/fcproto/message_pb2_grpc.py
farcaster/fcproto/onchain_event_pb2.py
farcaster/fcproto/onchain_event_pb2.pyi
farcaster/fcproto/onchain_event_pb2_grpc.py
farcaster/fcproto/request_response_pb2.py
farcaster/fcproto/request_response_pb2.pyi
farcaster/fcproto/request_response_pb2_grpc.py
farcaster/fcproto/rpc_pb2.py
farcaster/fcproto/rpc_pb2.pyi
farcaster/fcproto/rpc_pb2_grpc.py
farcaster/fcproto/sync_trie_pb2.py
farcaster/fcproto/sync_trie_pb2.pyi
farcaster/fcproto/sync_trie_pb2_grpc.py
farcaster/fcproto/username_proof_pb2.py
farcaster/fcproto/username_proof_pb2.pyi
farcaster/fcproto/username_proof_pb2_grpc.py
farcaster/schemas/gossip.proto
farcaster/schemas/hub_event.proto
farcaster/schemas/hub_state.proto
farcaster/schemas/job.proto
farcaster/schemas/message.proto
farcaster/schemas/onchain_event.proto
farcaster/schemas/request_response.proto
farcaster/schemas/rpc.proto
farcaster/schemas/sync_trie.proto
farcaster/schemas/username_proof.proto
farcaster_py-0.1.6.dist-info/METADATA
farcaster_py-0.1.6.dist-info/WHEEL
farcaster_py-0.1.6.dist-info/licenses/LICENSE
farcaster_py-0.1.6.dist-info/RECORD
