Metadata-Version: 2.3
Name: farcaster-py
Version: 0.1.6
Summary: Python bindings for Farcaster
Project-URL: Documentation, https://github.com/vrypan/farcaster-py#readme
Project-URL: Issues, https://github.com/vrypan/farcaster-py/issues
Project-URL: Source, https://github.com/vrypan/farcaster-py
Author-email: Panayotis Vryonis <vrypan@gmail.comm>
License-Expression: MIT
License-File: LICENSE
Classifier: Development Status :: 4 - Beta
Classifier: Programming Language :: Python
Requires-Python: >=3.10
Requires-Dist: aiohappyeyeballs==2.4.3
Requires-Dist: aiohttp==3.10.10
Requires-Dist: aiosignal==1.3.1
Requires-Dist: annotated-types==0.7.0
Requires-Dist: attrs==24.2.0
Requires-Dist: bitarray==2.9.3
Requires-Dist: certifi==2024.8.30
Requires-Dist: cffi==1.17.1
Requires-Dist: charset-normalizer==3.4.0
Requires-Dist: ckzg==2.0.1
Requires-Dist: cytoolz==1.0.0
Requires-Dist: eth-abi==5.1.0
Requires-Dist: eth-account==0.13.4
Requires-Dist: eth-hash==0.7.0
Requires-Dist: eth-keyfile==0.8.1
Requires-Dist: eth-keys==0.5.1
Requires-Dist: eth-rlp==2.1.0
Requires-Dist: eth-typing==5.0.1
Requires-Dist: eth-utils==5.0.0
Requires-Dist: frozenlist==1.4.1
Requires-Dist: grpcio==1.66.2
Requires-Dist: hexbytes==1.2.1
Requires-Dist: idna==3.10
Requires-Dist: importlib-resources>=6.4.5
Requires-Dist: multidict==6.1.0
Requires-Dist: parsimonious==0.10.0
Requires-Dist: propcache==0.2.0
Requires-Dist: protobuf==5.28.2
Requires-Dist: pycparser==2.22
Requires-Dist: pycryptodome==3.21.0
Requires-Dist: pydantic-core==2.23.4
Requires-Dist: pydantic==2.9.2
Requires-Dist: pynacl==1.5.0
Requires-Dist: pypandoc==1.14
Requires-Dist: python-dotenv==1.0.1
Requires-Dist: pyunormalize==16.0.0
Requires-Dist: regex==2024.9.11
Requires-Dist: requests==2.32.3
Requires-Dist: rlp==4.0.1
Requires-Dist: toolz==1.0.0
Requires-Dist: types-requests==2.32.0.20240914
Requires-Dist: typing-extensions==4.12.2
Requires-Dist: urllib3==2.2.3
Requires-Dist: web3==7.3.1
Requires-Dist: websockets==13.1
Requires-Dist: yarl==1.15.2
